xray/__init__.py
xray/junit_xml.py
xray/logger.py
xray/uploader.py
xray_uploader-2.8.1.dist-info/METADATA
xray_uploader-2.8.1.dist-info/WHEEL
xray_uploader-2.8.1.dist-info/entry_points.txt
xray_uploader-2.8.1.dist-info/top_level.txt
xray_uploader-2.8.1.dist-info/RECORD
