Metadata-Version: 2.4
Name: xray-uploader
Version: 2.8.1
Summary: upload test results to xray.
Author-email: qun <qun.chen@hexagon.com>
License: MIT License
Keywords: xray
Requires-Python: >=3.0
Requires-Dist: requests==2.31.0
